[
    {
      "value": "apple"
    },
    {
      "value": "banana"
    },
    {
      "value": "car"
    },
    {
      "value": "dog"
    },
    {
      "value": "elephant"
    },
    {
      "value": "fish"
    },
    {
      "value": "giraffe"
    },
    {
      "value": "house"
    },
    {
      "value": "ice cream"
    },
    {
      "value": "jacket"
    },
    {
      "value": "kite"
    },
    {
      "value": "lemon"
    },
    {
      "value": "monkey"
    },
    {
      "value": "notebook"
    },
    {
      "value": "orange"
    },
    {
      "value": "pizza"
    },
    {
      "value": "queen"
    },
    {
      "value": "rabbit"
    },
    {
      "value": "snake"
    },
    {
      "value": "tiger"
    },
    {
      "value": "umbrella"
    },
    {
      "value": "violin"
    },
    {
      "value": "watermelon"
    },
    {
      "value": "xylophone"
    },
    {
      "value": "yacht"
    },
    {
      "value": "zebra"
    },
    {
      "value": "airplane"
    },
    {
      "value": "bicycle"
    },
    {
      "value": "cupcake"
    },
    {
      "value": "dragon"
    },
    {
      "value": "egg"
    },
    {
      "value": "flamingo"
    },
    {
      "value": "grapes"
    },
    {
      "value": "hat"
    },
    {
      "value": "igloo"
    },
    {
      "value": "jam"
    },
    {
      "value": "kangaroo"
    },
    {
      "value": "lamp"
    },
    {
      "value": "mouse"
    },
    {
      "value": "nose"
    },
    {
      "value": "octopus"
    },
    {
      "value": "piano"
    },
    {
      "value": "quilt"
    },
    {
      "value": "rose"
    },
    {
      "value": "star"
    },
    {
      "value": "turtle"
    },
    {
      "value": "unicorn"
    },
    {
      "value": "vase"
    },
    {
      "value": "whale"
    },
    {
      "value": "xmas tree"
    },
    {
      "value": "yogurt"
    },
    {
      "value": "zucchini"
    },
    {
      "value": "aligator"
    },
    {
      "value": "beach"
    },
    {
      "value": "cat"
    },
    {
      "value": "drum"
    },
    {
      "value": "eleven"
    },
    {
      "value": "feather"
    },
    {
      "value": "guitar"
    },
    {
      "value": "honey"
    },
    {
      "value": "island"
    },
    {
      "value": "jackfruit"
    },
    {
      "value": "kettle"
    },
    {
      "value": "lion"
    },
    {
      "value": "mushroom"
    },
    {
      "value": "notepad"
    },
    {
      "value": "ocean"
    },
    {
      "value": "peacock"
    },
    {
      "value": "quokka"
    },
    {
      "value": "raccoon"
    },
    {
      "value": "snowman"
    },
    {
      "value": "toaster"
    },
    {
      "value": "ukulele"
    },
    {
      "value": "vulture"
    },
    {
      "value": "windmill"
    },
    {
      "value": "x-ray"
    },
    {
      "value": "yarn"
    },
    {
      "value": "zeppelin"
    },
    {
      "value": "ant"
    },
    {
      "value": "bunny"
    },
    {
      "value": "chocolate"
    },
    {
      "value": "dolphin"
    },
    {
      "value": "eggplant"
    },
    {
      "value": "fence"
    },
    {
      "value": "grapefruit"
    },
    {
      "value": "helicopter"
    },
    {
      "value": "iguanodon"
    },
    {
      "value": "jigsaw"
    },
    {
      "value": "kaleidoscope"
    },
    {
      "value": "lighthouse"
    },
    {
      "value": "moose"
    },
    {
      "value": "nutmeg"
    },
    {
      "value": "ostrich"
    },
    {
      "value": "pancake"
    },
    {
      "value": "quasar"
    },
    {
      "value": "robot"
    },
    {
      "value": "sandwich"
    },
    {
      "value": "trombone"
    },
    {
      "value": "utensil"
    },
    {
      "value": "viaduct"
    },
    {
      "value": "waffle"
    },
    {
      "value": "xerox"
    },
    {
      "value": "yeti"
    },
    {
      "value": "zucchini"
    }
  ]